espsetup.py
espsetup-0.0.6.data/scripts/espsetup.py
espsetup-0.0.6.dist-info/LICENSE.md
espsetup-0.0.6.dist-info/METADATA
espsetup-0.0.6.dist-info/WHEEL
espsetup-0.0.6.dist-info/top_level.txt
espsetup-0.0.6.dist-info/RECORD
