Metadata-Version: 2.1
Name: espsetup
Version: 0.0.6
Summary: simplified setup up for esp8266 / esp32 device
Home-page: https://github.com/kr-g/espsetup
Author: k. goger
Author-email: k.r.goger+espsetup@gmail.com
License: MIT
Keywords: micropython utility shell setup esp esp32 esp8266
Platform: UNKNOWN
Classifier: Development Status :: 3 - Alpha
Classifier: Operating System :: POSIX :: Linux
Classifier: Environment :: Console
Classifier: Intended Audience :: Developers
Classifier: Topic :: Software Development :: Embedded Systems
Classifier: Topic :: Terminals :: Serial
Classifier: Topic :: Utilities
Classifier: Programming Language :: Python :: 3
Classifier: License :: OSI Approved :: MIT License
Requires-Python: >=3.6
Requires-Dist: esptool
